mintool/__init__.py
mintool/file/__init__.py
mintool/file/read.py
mintool-2025.2.18.dist-info/LICENSE
mintool-2025.2.18.dist-info/METADATA
mintool-2025.2.18.dist-info/WHEEL
mintool-2025.2.18.dist-info/top_level.txt
mintool-2025.2.18.dist-info/RECORD
