Metadata-Version: 2.2
Name: mintool
Version: 2025.2.18
Summary: A simple package for commonly used utilities.
Author: JialinMin
Project-URL: Repository, https://github.com/JLMin/mintool
Classifier: Programming Language :: Python :: 3.8
Classifier: License :: OSI Approved :: MIT License
Classifier: Operating System :: OS Independent
Requires-Python: >=3.8
License-File: LICENSE
